madchappy/__init__.py
madchappy/helpers.py
madchappy/requests_wrap.py
madchappy/vault_wrap.py
madchappy-0.3.dist-info/METADATA
madchappy-0.3.dist-info/WHEEL
madchappy-0.3.dist-info/top_level.txt
madchappy-0.3.dist-info/RECORD
