Metadata-Version: 2.1
Name: madchappy
Version: 0.3
Summary: Private collection of python stuff
Home-page: https://gitlab.com/fred.blaise/madchappy
Author: Fred Blaise
Author-email: fred.blaise@gmail.com
License: MIT
Platform: UNKNOWN
Requires-Dist: requests (==2.19.1)
Requires-Dist: hvac (==0.6.4)
